balkhash/__init__.py
balkhash/cli.py
balkhash/dataset.py
balkhash/leveldb.py
balkhash/memorious.py
balkhash/postgres.py
balkhash/settings.py
balkhash/utils.py
balkhash-1.2.1.dist-info/LICENSE
balkhash-1.2.1.dist-info/METADATA
balkhash-1.2.1.dist-info/WHEEL
balkhash-1.2.1.dist-info/entry_points.txt
balkhash-1.2.1.dist-info/namespace_packages.txt
balkhash-1.2.1.dist-info/top_level.txt
balkhash-1.2.1.dist-info/zip-safe
balkhash-1.2.1.dist-info/RECORD
